MANIFEST.in
README.txt
setup.py
XStatic_Chart.js.egg-info/PKG-INFO
XStatic_Chart.js.egg-info/SOURCES.txt
XStatic_Chart.js.egg-info/dependency_links.txt
XStatic_Chart.js.egg-info/namespace_packages.txt
XStatic_Chart.js.egg-info/not-zip-safe
XStatic_Chart.js.egg-info/top_level.txt
xstatic/__init__.py
xstatic/pkg/__init__.py
xstatic/pkg/chart_js/__init__.py
xstatic/pkg/chart_js/__init__.pyc
xstatic/pkg/chart_js/data/Chart.js
xstatic/pkg/chart_js/data/Chart.min.js