Metadata-Version: 1.0
Name: XStatic-Chart.js
Version: 1.0.2.2
Summary: Chart.js 1.0.2 (XStatic packaging standard)
Home-page: https://github.com/nnnick/Chart.js
Author: Benjamin Dauvergne
Author-email: bdauvergne@entrouvert.com
License: (same as Chart.js)
Keywords: chart_js xstatic
Platform: any
